{
  "schema_version": 1,
  "notes": [
    {
      "owner_id": "",
      "id": "613307d0-5fcb-4b8f-87c6-f2740ae24958",
      "tags": [],
      "word_count": 0,
      "title": "Test Note Manual",
      "created": "2025-12-17T11:36:11.0000000",
      "owner_type": "global",
      "modified": "2025-12-17T11:36:11.0000000",
      "file": "/home/teej/ztest/module/notes/613307d0-5fcb-4b8f-87c6-f2740ae24958.txt",
      "line_count": 0
    },
    {
      "owner_id": "",
      "id": "28069655-c988-4b17-b91f-54bfd7c1293a",
      "tags": [],
      "word_count": 1,
      "title": "Test Note Manual",
      "created": "2025-12-17T10:08:09.0000000",
      "owner_type": "global",
      "modified": "2025-12-17T10:08:11.0000000",
      "file": "/home/teej/ztest/module/notes/28069655-c988-4b17-b91f-54bfd7c1293a.txt",
      "line_count": 2
    },
    {
      "owner_id": "",
      "id": "33d7d2dd-910f-4040-8972-d11b5200cd8a",
      "tags": [],
      "word_count": 7,
      "title": "2",
      "created": "2025-12-11T13:05:57.0000000",
      "owner_type": "global",
      "modified": "2025-12-11T13:07:58.0000000",
      "file": "C:\\Users\\jhnhe\\OneDrive\\Documents\\GitHub\\project-management-console\\HYBRID\\module\\notes\\33d7d2dd-910f-4040-8972-d11b5200cd8a.txt",
      "line_count": 4
    },
    {
      "owner_id": "",
      "id": "0f32fa4c-1cf1-4653-91c8-b0ea43c557ba",
      "tags": [],
      "word_count": 0,
      "title": "Test Note Manual",
      "created": "2025-12-17T11:40:20.0000000",
      "owner_type": "global",
      "modified": "2025-12-17T11:40:20.0000000",
      "file": "/home/teej/ztest/module/notes/0f32fa4c-1cf1-4653-91c8-b0ea43c557ba.txt",
      "line_count": 0
    },
    {
      "owner_id": "",
      "id": "95fd9a31-57ad-4da1-8466-70b25a3667f4",
      "tags": [],
      "word_count": 0,
      "title": "Test Note Manual",
      "created": "2025-12-17T10:07:41.0000000",
      "owner_type": "global",
      "modified": "2025-12-17T10:07:41.0000000",
      "file": "/home/teej/ztest/module/notes/95fd9a31-57ad-4da1-8466-70b25a3667f4.txt",
      "line_count": 0
    },
    {
      "owner_id": "",
      "id": "22e5ce4c-9814-4c76-bb51-771b3f46e6a8",
      "tags": [],
      "word_count": 0,
      "title": "Test Note Manual",
      "created": "2025-12-17T13:05:25.0000000",
      "owner_type": "global",
      "modified": "2025-12-17T13:05:25.0000000",
      "file": "/home/teej/ztest/module/notes/22e5ce4c-9814-4c76-bb51-771b3f46e6a8.txt",
      "line_count": 0
    },
    {
      "owner_id": "",
      "id": "99827c19-0e3a-41f3-8d57-a60db1e23c51",
      "tags": [],
      "word_count": 0,
      "title": "Test Live Note",
      "created": "2025-12-17T11:47:36.0000000",
      "owner_type": "global",
      "modified": "2025-12-17T11:47:36.0000000",
      "file": "/home/teej/ztest/module/notes/99827c19-0e3a-41f3-8d57-a60db1e23c51.txt",
      "line_count": 0
    },
    {
      "owner_id": "",
      "id": "144d354f-256d-4ef5-9b0d-468883779142",
      "tags": [],
      "word_count": 0,
      "title": "Test Note Manual",
      "created": "2025-12-17T11:44:19.0000000",
      "owner_type": "global",
      "modified": "2025-12-17T11:44:19.0000000",
      "file": "/home/teej/ztest/module/notes/144d354f-256d-4ef5-9b0d-468883779142.txt",
      "line_count": 0
    },
    {
      "owner_id": "",
      "id": "be9a15ee-2ffd-4341-a618-33cb8baa6c49",
      "tags": [],
      "word_count": 0,
      "title": "Test Note Manual",
      "created": "2025-12-17T10:09:50.0000000",
      "owner_type": "global",
      "modified": "2025-12-17T10:09:50.0000000",
      "file": "/home/teej/ztest/module/notes/be9a15ee-2ffd-4341-a618-33cb8baa6c49.txt",
      "line_count": 0
    },
    {
      "owner_id": "",
      "id": "f75186f1-0bd8-4fc9-bc6f-17457dcda2f6",
      "tags": [],
      "word_count": 0,
      "title": "Test Note Manual",
      "created": "2025-12-17T10:10:19.0000000",
      "owner_type": "global",
      "modified": "2025-12-17T10:10:19.0000000",
      "file": "/home/teej/ztest/module/notes/f75186f1-0bd8-4fc9-bc6f-17457dcda2f6.txt",
      "line_count": 0
    },
    {
      "owner_id": "",
      "id": "fc248f8e-797a-4b2a-bd02-f3ac4907b3d3",
      "tags": [],
      "word_count": 0,
      "title": "Test Note Manual",
      "created": "2025-12-17T11:36:55.0000000",
      "owner_type": "global",
      "modified": "2025-12-17T11:36:55.0000000",
      "file": "/home/teej/ztest/module/notes/fc248f8e-797a-4b2a-bd02-f3ac4907b3d3.txt",
      "line_count": 0
    },
    {
      "owner_id": "",
      "id": "fe0d9893-764c-4609-87a8-8c3eda2f94b6",
      "tags": [],
      "word_count": 0,
      "title": "Test Note Manual",
      "created": "2025-12-17T10:07:16.0000000",
      "owner_type": "global",
      "modified": "2025-12-17T10:07:16.0000000",
      "file": "/home/teej/ztest/module/notes/fe0d9893-764c-4609-87a8-8c3eda2f94b6.txt",
      "line_count": 0
    },
    {
      "owner_id": "",
      "id": "ebd043bc-6148-4908-b1c1-a12988524c8d",
      "tags": [],
      "word_count": 0,
      "title": "Test Note Manual",
      "created": "2025-12-17T10:09:22.0000000",
      "owner_type": "global",
      "modified": "2025-12-17T10:09:22.0000000",
      "file": "/home/teej/ztest/module/notes/ebd043bc-6148-4908-b1c1-a12988524c8d.txt",
      "line_count": 0
    },
    {
      "owner_id": "",
      "id": "c393c8de-3a0a-460e-9f81-0c4ee9855b3b",
      "tags": [],
      "word_count": 0,
      "title": "Test Note Manual",
      "created": "2025-12-17T13:03:00.0000000",
      "owner_type": "global",
      "modified": "2025-12-17T13:03:00.0000000",
      "file": "/home/teej/ztest/module/notes/c393c8de-3a0a-460e-9f81-0c4ee9855b3b.txt",
      "line_count": 0
    },
    {
      "owner_id": "",
      "id": "f6e39bb2-eb08-416b-9096-8c9f8730cbfe",
      "tags": [],
      "word_count": 0,
      "title": "Test Note Manual",
      "created": "2025-12-17T10:06:50.0000000",
      "owner_type": "global",
      "modified": "2025-12-17T10:06:50.0000000",
      "file": "/home/teej/ztest/module/notes/f6e39bb2-eb08-416b-9096-8c9f8730cbfe.txt",
      "line_count": 0
    },
    {
      "owner_id": "",
      "id": "a272d1c3-b0db-4ad0-98bc-be6704fc78f1",
      "tags": [],
      "word_count": 2,
      "title": "n1",
      "created": "2025-12-17T13:13:11.0000000",
      "owner_type": "global",
      "modified": "2025-12-17T13:54:59.2614151-07:00",
      "file": "/home/teej/ztest/module/notes/a272d1c3-b0db-4ad0-98bc-be6704fc78f1.txt",
      "line_count": 3
    },
    {
      "owner_id": "",
      "id": "17d2746e-0146-4194-aeb3-08bcd0af8f1c",
      "tags": [],
      "word_count": 0,
      "title": "Test Note Manual",
      "created": "2025-12-17T11:43:42.0000000",
      "owner_type": "global",
      "modified": "2025-12-17T11:43:42.0000000",
      "file": "/home/teej/ztest/module/notes/17d2746e-0146-4194-aeb3-08bcd0af8f1c.txt",
      "line_count": 0
    },
    {
      "owner_id": "",
      "id": "2553b2ef-b5a8-4cdb-889b-90d23a9f9c4a",
      "tags": [],
      "word_count": 3,
      "title": "1",
      "created": "2025-12-10T22:24:30.0000000",
      "owner_type": "global",
      "modified": "2025-12-11T11:06:59.0000000",
      "file": "C:\\Users\\jhnhe\\OneDrive\\Documents\\GitHub\\project-management-console\\og_transport\\working\\module\\notes\\2553b2ef-b5a8-4cdb-889b-90d23a9f9c4a.txt",
      "line_count": 4
    },
    {
      "owner_id": "",
      "id": "095be222-48a2-49dd-88ea-14e8ba946d50",
      "tags": [],
      "word_count": 0,
      "title": "Test Note Manual",
      "created": "2025-12-17T11:41:47.0000000",
      "owner_type": "global",
      "modified": "2025-12-17T11:41:47.0000000",
      "file": "/home/teej/ztest/module/notes/095be222-48a2-49dd-88ea-14e8ba946d50.txt",
      "line_count": 0
    }
  ]
}
